kafka_client/__init__.py
kafka_client/__version__.py
kafka_client/consumer.py
kafka_client/handler.py
kafka_client/kafka_client_exception.py
kafka_client/manager.py
kafka_client/message.py
kafka_client/producer.py
kafka_client_new-0.4.dev2.dist-info/METADATA
kafka_client_new-0.4.dev2.dist-info/WHEEL
kafka_client_new-0.4.dev2.dist-info/RECORD
