Metadata-Version: 2.1
Name: kafka-client-new
Version: 0.4.dev2
Summary: 
Author: Mark Poroshin
Author-email: mporoshin@smartpredictiontech.ru
Requires-Python: >=3.9,<3.13
Classifier: Programming Language :: Python :: 3
Classifier: Programming Language :: Python :: 3.9
Classifier: Programming Language :: Python :: 3.10
Classifier: Programming Language :: Python :: 3.11
Classifier: Programming Language :: Python :: 3.12
Requires-Dist: apscheduler (>=3.10.1,<4.0.0)
Requires-Dist: kafka-python (>=2.0.2,<3.0.0)
Requires-Dist: lz4 (>=4.3.2,<5.0.0)
Requires-Dist: pandas (>=2.1.1,<3.0.0)
Requires-Dist: prometheus-client (==0.15.0)
